netflix/__init__.py
netflix/__main__.py
netflix/cli.py
netflix/netflix.py
rlane_netflix-1.0.6.dist-info/METADATA
rlane_netflix-1.0.6.dist-info/WHEEL
rlane_netflix-1.0.6.dist-info/entry_points.txt
rlane_netflix-1.0.6.dist-info/licenses/LICENSE
rlane_netflix-1.0.6.dist-info/RECORD
