Metadata-Version: 2.1
Name: rlane-netflix
Version: 1.0.6
Summary: Netflix history report
Keywords: netflix,python
Author-Email: Russel Lane <russel@rlane.com>
License: MIT
Classifier: Development Status :: 4 - Beta
Classifier: Intended Audience :: End Users/Desktop
Classifier: License :: OSI Approved :: MIT License
Classifier: Programming Language :: Python :: 3
Classifier: Topic :: Text Processing :: General
Project-URL: Homepage, https://github.com/russellane/netflix
Requires-Python: >=3.10
Requires-Dist: rlane-libcli>=1.0.8
